goalchain/__init__.py
goalchain/goalchain.py
goalchain-0.0.3.dist-info/METADATA
goalchain-0.0.3.dist-info/WHEEL
goalchain-0.0.3.dist-info/licenses/LICENSE
goalchain-0.0.3.dist-info/RECORD
